minder/dataset_manager/__init__.py
minder/dataset_manager/_preprocessor.py
minder/dataset_manager/_utils/__init__.py
minder/dataset_manager/_utils/_composed_dataset.py
minder/dataset_manager/_utils/_dataset.py
minder/dataset_manager/datasets/__init__.py
minder/dataset_manager/datasets/_labelled_uti_dataset.py
minder/dataset_manager/datasets/_unlabelled_uti_dataset.py
minder/dataset_manager/datasets/_uti_labels_dataset.py
minder/dataset_manager/py.typed
minder.dataset_manager-0.1.0.dist-info/WHEEL
minder.dataset_manager-0.1.0.dist-info/METADATA
minder.dataset_manager-0.1.0.dist-info/RECORD
