Metadata-Version: 2.1
Name: minder.dataset-manager
Version: 0.1.0
Summary: 
Author: UK DRI Care Research & Technology centre
Requires-Python: >=3.8,<4.0
Classifier: Programming Language :: Python :: 3
Classifier: Programming Language :: Python :: 3.10
Classifier: Programming Language :: Python :: 3.8
Classifier: Programming Language :: Python :: 3.9
Requires-Dist: minder.research-portal-client (>=0.1.3,<0.2.0)
Requires-Dist: numpy (>=1.22.4,<2.0.0)
Requires-Dist: pandas (>=1.4.2,<2.0.0)
